{
  "gitSyncId": "66caf0c06df6cc55d47776cf_f3d3d019-0fd8-43f2-b6b0-08d0cf2a945e",
  "id": "Home_visitors",
  "pluginId": "postgres-plugin",
  "pluginType": "DB",
  "unpublishedAction": {
    "actionConfiguration": {
      "body": "CREATE TABLE IF NOT EXISTS visitors (\n    id SERIAL PRIMARY KEY,\n    time TIMESTAMP DEFAULT CURRENT_TIMESTAMP,\n    ip_address VARCHAR(45)\n);\n\nINSERT INTO visitors (time, ip_address) VALUES (DEFAULT, {{this.params.ip}});\n",
      "encodeParamsToggle": true,
      "paginationType": "NONE",
      "pluginSpecifiedTemplates": [
        {
          "value": true
        }
      ],
      "timeoutInMillisecond": 10000
    },
    "confirmBeforeExecute": false,
    "datasource": {
      "id": "AWS RDS Postgres",
      "isAutoGenerated": false,
      "name": "AWS RDS Postgres",
      "pluginId": "postgres-plugin"
    },
    "dynamicBindingPathList": [
      {
        "key": "body"
      }
    ],
    "executeOnLoad": false,
    "name": "visitors",
    "pageId": "Home",
    "userSetOnLoad": false
  }
}